README.rst
setup.py
glim_extensions/__init__.py
glim_extensions.egg-info/PKG-INFO
glim_extensions.egg-info/SOURCES.txt
glim_extensions.egg-info/dependency_links.txt
glim_extensions.egg-info/requires.txt
glim_extensions.egg-info/top_level.txt
glim_extensions/db/__init__.py
glim_extensions/db/commands.py
glim_extensions/db/db.py
glim_extensions/db/migration.py
glim_extensions/db/models.py
glim_extensions/db/start.py
glim_extensions/db/utils.py
glim_extensions/gredis/__init__.py
glim_extensions/gredis/exception.py
glim_extensions/gredis/gredis.py
glim_extensions/gredis/start.py
glim_extensions/job/__init__.py
glim_extensions/job/commands.py
glim_extensions/job/exception.py
glim_extensions/job/job.py
glim_extensions/job/queue.py
glim_extensions/job/start.py
glim_extensions/jslint/__init__.py
glim_extensions/jslint/jslint.py
glim_extensions/jslint/start.py
glim_extensions/less/__init__.py
glim_extensions/less/less.py
glim_extensions/less/start.py
glim_extensions/memcached/__init__.py
glim_extensions/memcached/memcached.py
glim_extensions/memcached/start.py
glim_extensions/view/__init__.py
glim_extensions/view/commands.py
glim_extensions/view/start.py
glim_extensions/view/view.py