Metadata-Version: 1.1
Name: glim-extensions
Version: 0.3.0
Summary: Glim Extensions
Home-page: https://github.com/aacanakin/glim-extensions
Author: Aras Can Akin
Author-email: aacanakin@gmail.com
License: UNKNOWN
Download-URL: https://github.com/aacanakin/glim-extensions/archive/v0.3.0.zip
Keywords: framework,web framework,extensions,redis,job queue,SQLAlchemy,Jinja2,mail queue,jslint,less
Platform: UNKNOWN
Classifier: Development Status :: 3 - Alpha
Classifier: Environment :: Web Environment
Classifier: Intended Audience :: Developers
Classifier: License :: OSI Approved :: MIT License
Classifier: Operating System :: OS Independent
Classifier: Programming Language :: Python
Classifier: Topic :: Software Development :: Libraries :: Python Modules
